pyo3_mixed-2.1.5.dist-info/METADATA
pyo3_mixed-2.1.5.dist-info/WHEEL
pyo3_mixed-2.1.5.dist-info/entry_points.txt
pyo3_mixed/python_module/__init__.py
pyo3_mixed/python_module/double.py
pyo3_mixed/__init__.py
pyo3_mixed/pyo3_mixed.cpython-311-x86_64-linux-gnu.so
pyo3_mixed-2.1.5.dist-info/RECORD
