Metadata-Version: 2.3
Name: pyo3-mixed
Version: 2.1.5
Classifier: Programming Language :: Python
Classifier: Programming Language :: Rust
Requires-Dist: boltons
Summary: Implements a dummy function combining rust and python
Author: konstin <konstin@mailbox.org>
Author-email: konstin <konstin@mailbox.org>
Requires-Python: >=3.7
